parcp2.py
setup.py
parcp/__init__.py
parcp/cpimages.py
parcp/version.py
parcp.egg-info/PKG-INFO
parcp.egg-info/SOURCES.txt
parcp.egg-info/dependency_links.txt
parcp.egg-info/pbr.json
parcp.egg-info/requires.txt
parcp.egg-info/top_level.txt