Metadata-Version: 1.1
Name: parcp
Version: 0.2.1
Summary: A library to run CellProfiler in parallel
Home-page: https://github.com/ewiger/parcp
Author: Yauhen Yakimovich
Author-email: eugeny.yakimovitch@gmail.com
License: MIT
Download-URL: https://github.com/ewiger//tarball/master
Platform: Linux
Platform: OS-X
Classifier: Topic :: System :: Distributed Computing
Classifier: Topic :: Scientific/Engineering :: Image Recognition
Classifier: Topic :: Scientific/Engineering :: Information Analysis
Classifier: Intended Audience :: Developers
Classifier: Intended Audience :: System Administrators
Classifier: Programming Language :: Python
Classifier: Programming Language :: Unix Shell
Classifier: Development Status :: 4 - Beta
Classifier: Operating System :: POSIX :: Linux
Classifier: Operating System :: MacOS
